open_exchange/__init__.py
open_exchange/client.py
open_exchange/compat.py
open_exchange/contants.py
open_exchange/exceptions.py
open_exchange/resource.py
open_exchange/typing.py
open_exchange/resources/__init__.py
open_exchange/resources/data/__init__.py
open_exchange/resources/data/data.py
open_exchange/resources/data/property_details.py
open_exchange/resources/data/property_values.py
open_exchange/resources/data/rent_estimates.py
open_exchange/resources/data/rental_comps.py
open_exchange/types/__init__.py
open_exchange/types/models.py
open_exchange/types/data/__init__.py
open_exchange/types/data/property_details_fetch_params.py
open_exchange/types/data/property_details_response.py
open_exchange/types/data/property_values_fetch_params.py
open_exchange/types/data/property_values_response.py
open_exchange/types/data/rent_estimates_fetch_params.py
open_exchange/types/data/rent_estimates_response.py
open_exchange/types/data/rental_comps_fetch_params.py
open_exchange/types/data/rental_comps_response.py
open_exchange-0.2.0.dist-info/LICENSE.md
open_exchange-0.2.0.dist-info/WHEEL
open_exchange-0.2.0.dist-info/METADATA
open_exchange-0.2.0.dist-info/RECORD
