Metadata-Version: 2.1
Name: open-exchange
Version: 0.2.0
Summary: Open Exchange Python SDK.
Author-email: "Open Exchange Labs, Inc." <ox-data-eng@opendoor.com>
Requires-Python: >=3.6.2,<4.0.0
Classifier: Development Status :: 3 - Alpha
Classifier: Programming Language :: Python
Classifier: Programming Language :: Python :: 3
Classifier: Programming Language :: Python :: 3 :: Only
Classifier: Programming Language :: Python :: 3.6
Classifier: Programming Language :: Python :: 3.7
Classifier: Programming Language :: Python :: 3.8
Classifier: Programming Language :: Python :: 3.9
Classifier: Programming Language :: Python :: 3.10
Classifier: Programming Language :: Python :: 3.11
Classifier: Programming Language :: Python :: 3.12
Classifier: Intended Audience :: Developers
Classifier: Intended Audience :: Information Technology
Classifier: License :: OSI Approved :: MIT License
Classifier: Operating System :: OS Independent
Classifier: Topic :: Software Development :: Libraries :: Python Modules
Requires-Dist: cached-property>=1.5.2; python_version<'3.8'
Requires-Dist: pydantic>=1.9.2
Requires-Dist: requests>=2.27.1
Requires-Dist: urllib3>=1.21.1
Project-URL: Home, https://github.com/opendoor-labs/open-exchange-python
